Workbook

Sheet Assumptions
A1: DEMOCO — ASSUMPTIONS
A3: REVENUE DRIVERS
A4: Units sold Y1 | B4: 1000
A5: Unit growth % | B5: 0.12
A6: Price / unit | B6: 25
A7: Price growth % | B7: 0.03
A9: COST DRIVERS
A10: COGS % of revenue | B10: 0.42
A11: Opex fixed | B11: 4000
A12: Opex % of revenue | B12: 0.08
A14: CAPEX & DEPRECIATION
A15: Capex % of revenue | B15: 0.05
A16: Depreciation years | B16: 5
A18: WORKING CAPITAL & TAX
A19: DSO days | B19: 45
A20: DPO days | B20: 30
A21: Tax rate | B21: 0.2
A23: DEBT
A24: Opening debt | B24: 8000
A25: Interest rate | B25: 0.07
A26: Annual repayment | B26: 1000

Sheet Revenue Build
A1: DEMOCO — REVENUE BUILD
A2: Year | B2: 1 | C2: 2 | D2: 3 | E2: 4 | F2: 5
A3: Units | B3: =Assumptions!B4 | C3: =B3*(1+Assumptions!$B$5) | D3: =C3*(1+Assumptions!$B$5) | E3: =D3*(1+Assumptions!$B$5) | F3: =E3*(1+Assumptions!$B$5)
A4: Price | B4: =Assumptions!B6 | C4: =B4*(1+Assumptions!$B$7) | D4: =C4*(1+Assumptions!$B$7) | E4: =D4*(1+Assumptions!$B$7) | F4: =E4*(1+Assumptions!$B$7)
A5: Revenue | B5: =B3*B4 | C5: =C3*C4 | D5: =D3*D4 | E5: =E3*E4 | F5: =F3*F4

Sheet Cost Build
A1: DEMOCO — COST BUILD
A2: Year | B2: 1 | C2: 2 | D2: 3 | E2: 4 | F2: 5
A3: COGS | B3: ='Revenue Build'!B5*Assumptions!$B$10 | C3: ='Revenue Build'!C5*Assumptions!$B$10 | D3: ='Revenue Build'!D5*Assumptions!$B$10 | E3: ='Revenue Build'!E5*Assumptions!$B$10 | F3: ='Revenue Build'!F5*Assumptions!$B$10
A4: Opex | B4: =Assumptions!$B$11+'Revenue Build'!B5*Assumptions!$B$12 | C4: =Assumptions!$B$11+'Revenue Build'!C5*Assumptions!$B$12 | D4: =Assumptions!$B$11+'Revenue Build'!D5*Assumptions!$B$12 | E4: =Assumptions!$B$11+'Revenue Build'!E5*Assumptions!$B$12 | F4: =Assumptions!$B$11+'Revenue Build'!F5*Assumptions!$B$12
A5: Capex | B5: ='Revenue Build'!B5*Assumptions!$B$15 | C5: ='Revenue Build'!C5*Assumptions!$B$15 | D5: ='Revenue Build'!D5*Assumptions!$B$15 | E5: ='Revenue Build'!E5*Assumptions!$B$15 | F5: ='Revenue Build'!F5*Assumptions!$B$15
A6: Depreciation | B6: =SUM($B$5:B5)/Assumptions!$B$16 | C6: =SUM($B$5:C5)/Assumptions!$B$16 | D6: =SUM($B$5:D5)/Assumptions!$B$16 | E6: =SUM($B$5:E5)/Assumptions!$B$16 | F6: =SUM($B$5:F5)/Assumptions!$B$16

Sheet Debt Schedule
A1: DEMOCO — DEBT SCHEDULE
A2: Year | B2: 1 | C2: 2 | D2: 3 | E2: 4 | F2: 5
A3: Opening debt | B3: =Assumptions!B22 | C3: =B5 | D3: =C5 | E3: =D5 | F3: =E5
A4: Repayment | B4: =MIN(Assumptions!$B$24,B3) | C4: =MIN(Assumptions!$B$24,C3) | D4: =MIN(Assumptions!$B$24,D3) | E4: =MIN(Assumptions!$B$24,E3) | F4: =MIN(Assumptions!$B$24,F3)
A5: Closing debt | B5: =B3-B4 | C5: =C3-C4 | D5: =D3-D4 | E5: =E3-E4 | F5: =F3-F4
A6: Interest | B6: =B3*Assumptions!$B$23 | C6: =C3*Assumptions!$B$23 | D6: =D3*Assumptions!$B$23 | E6: =E3*Assumptions!$B$23 | F6: =F3*Assumptions!$B$23

Sheet P&L
A1: DEMOCO — P&L
A2: Year | B2: 1 | C2: 2 | D2: 3 | E2: 4 | F2: 5
A3: Revenue | B3: ='Revenue Build'!B5 | C3: ='Revenue Build'!C5 | D3: ='Revenue Build'!D5 | E3: ='Revenue Build'!E5 | F3: ='Revenue Build'!F5
A4: COGS | B4: ='Cost Build'!B3 | C4: ='Cost Build'!C3 | D4: ='Cost Build'!D3 | E4: ='Cost Build'!E3 | F4: ='Cost Build'!F3
A5: Gross profit | B5: =B3-B4 | C5: =C3-C4 | D5: =D3-D4 | E5: =E3-E4 | F5: =F3-F4
A6: Opex | B6: ='Cost Build'!B4 | C6: ='Cost Build'!C4 | D6: ='Cost Build'!D4 | E6: ='Cost Build'!E4 | F6: ='Cost Build'!F4
A7: EBITDA | B7: =B5-B6 | C7: =C5-C6 | D7: =D5-D6 | E7: =E5-E6 | F7: =F5-F6
A8: Depreciation | B8: ='Cost Build'!B6 | C8: ='Cost Build'!C6 | D8: ='Cost Build'!D6 | E8: ='Cost Build'!E6 | F8: ='Cost Build'!F6
A9: EBIT | B9: =B7-B8 | C9: =C7-C8 | D9: =D7-D8 | E9: =E7-E8 | F9: =F7-F8
A10: Interest | B10: ='Debt Schedule'!B6 | C10: ='Debt Schedule'!C6 | D10: ='Debt Schedule'!D6 | E10: ='Debt Schedule'!E6 | F10: ='Debt Schedule'!F6
A11: PBT | B11: =B9-B10 | C11: =C9-C10 | D11: =D9-D10 | E11: =E9-E10 | F11: =F9-F10
A12: Tax | B12: =MAX(B11,0)*Assumptions!$B$19 | C12: =MAX(C11,0)*Assumptions!$B$19 | D12: =MAX(D11,0)*Assumptions!$B$19 | E12: =MAX(E11,0)*Assumptions!$B$19 | F12: =MAX(F11,0)*Assumptions!$B$19
A13: Net income | B13: =B11-B12 | C13: =C11-C12 | D13: =D11-D12 | E13: =E11-E12 | F13: =F11-F12

Sheet Cash Flow
A1: DEMOCO — CASH FLOW
A2: Year | B2: 1 | C2: 2 | D2: 3 | E2: 4 | F2: 5
A3: Net income | B3: ='P&L'!B13 | C3: ='P&L'!C13 | D3: ='P&L'!D13 | E3: ='P&L'!E13 | F3: ='P&L'!F13
A4: Add back D&A | B4: ='Cost Build'!B6 | C4: ='Cost Build'!C6 | D4: ='Cost Build'!D6 | E4: ='Cost Build'!E6 | F4: ='Cost Build'!F6
A5: Change in WC | B5: =-('P&L'!B3*Assumptions!$B$18/365-'P&L'!B4*Assumptions!$B$19/365) | C5: =-('P&L'!C3*Assumptions!$B$18/365-'P&L'!C4*Assumptions!$B$19/365) | D5: =-('P&L'!D3*Assumptions!$B$18/365-'P&L'!D4*Assumptions!$B$19/365) | E5: =-('P&L'!E3*Assumptions!$B$18/365-'P&L'!E4*Assumptions!$B$19/365) | F5: =-('P&L'!F3*Assumptions!$B$18/365-'P&L'!F4*Assumptions!$B$19/365)
A6: Capex | B6: =-'Cost Build'!B5 | C6: =-'Cost Build'!C5 | D6: =-'Cost Build'!D5 | E6: =-'Cost Build'!E5 | F6: =-'Cost Build'!F5
A7: Debt repayment | B7: =-'Debt Schedule'!B4 | C7: =-'Debt Schedule'!C4 | D7: =-'Debt Schedule'!D4 | E7: =-'Debt Schedule'!E4 | F7: =-'Debt Schedule'!F4
A8: Net cash flow | B8: =SUM(B3:B7) | C8: =SUM(C3:C7) | D8: =SUM(D3:D7) | E8: =SUM(E3:E7) | F8: =SUM(F3:F7)
A9: Cash balance | B9: =B8 | C9: =B9+C8 | D9: =C9+D8 | E9: =D9+E8 | F9: =E9+F8

Sheet Returns
A1: DEMOCO — RETURNS
A2: Exit multiple (hardcoded!)
A3: Exit EBITDA | B3: ='P&L'!F7*8.5
A4: Enterprise value | B4: =B3
A5: Net debt at exit | B5: ='Debt Schedule'!F5-'Cash Flow'!F9
A6: Equity value | B6: =B4-B5
